diffusers/__init__.py
diffusers/configuration_utils.py
diffusers/dependency_versions_check.py
diffusers/dependency_versions_table.py
diffusers/image_processor.py
diffusers/loaders.py
diffusers/optimization.py
diffusers/pipeline_utils.py
diffusers/training_utils.py
diffusers/commands/__init__.py
diffusers/commands/diffusers_cli.py
diffusers/commands/env.py
diffusers/experimental/__init__.py
diffusers/experimental/rl/__init__.py
diffusers/experimental/rl/value_guided_sampling.py
diffusers/models/__init__.py
diffusers/models/attention.py
diffusers/models/attention_flax.py
diffusers/models/attention_processor.py
diffusers/models/autoencoder_kl.py
diffusers/models/controlnet.py
diffusers/models/controlnet_flax.py
diffusers/models/cross_attention.py
diffusers/models/dual_transformer_2d.py
diffusers/models/embeddings.py
diffusers/models/embeddings_flax.py
diffusers/models/modeling_flax_pytorch_utils.py
diffusers/models/modeling_flax_utils.py
diffusers/models/modeling_pytorch_flax_utils.py
diffusers/models/modeling_utils.py
diffusers/models/prior_transformer.py
diffusers/models/resnet.py
diffusers/models/resnet_flax.py
diffusers/models/t5_film_transformer.py
diffusers/models/transformer_2d.py
diffusers/models/transformer_temporal.py
diffusers/models/unet_1d.py
diffusers/models/unet_1d_blocks.py
diffusers/models/unet_2d.py
diffusers/models/unet_2d_blocks.py
diffusers/models/unet_2d_blocks_flax.py
diffusers/models/unet_2d_condition.py
diffusers/models/unet_2d_condition_flax.py
diffusers/models/unet_3d_blocks.py
diffusers/models/unet_3d_condition.py
diffusers/models/vae.py
diffusers/models/vae_flax.py
diffusers/models/vq_model.py
diffusers/pipelines/__init__.py
diffusers/pipelines/onnx_utils.py
diffusers/pipelines/pipeline_flax_utils.py
diffusers/pipelines/pipeline_utils.py
diffusers/pipelines/alt_diffusion/__init__.py
diffusers/pipelines/alt_diffusion/modeling_roberta_series.py
diffusers/pipelines/alt_diffusion/pipeline_alt_diffusion.py
diffusers_unchained-0.16.2.dist-info/LICENSE
diffusers_unchained-0.16.2.dist-info/METADATA
diffusers_unchained-0.16.2.dist-info/WHEEL
diffusers_unchained-0.16.2.dist-info/entry_points.txt
diffusers_unchained-0.16.2.dist-info/top_level.txt
diffusers_unchained-0.16.2.dist-info/RECORD
